README.rst
peewee_mssqlserv.py
setup.py
peewee_mssqlserv.egg-info/PKG-INFO
peewee_mssqlserv.egg-info/SOURCES.txt
peewee_mssqlserv.egg-info/dependency_links.txt
peewee_mssqlserv.egg-info/requires.txt
peewee_mssqlserv.egg-info/top_level.txt