Metadata-Version: 1.1
Name: peewee-mssqlserv
Version: 0.1.5
Summary: MS SQL Server support for the peewee ORM
Home-page: https://github.com/brake/peewee_mssql
Author: Constantin Roganov
Author-email: rccbox@gmail.com
License: UNKNOWN
Download-URL: https://github.com/brake/peewee_mssql/archive/0.1.5.zip
Keywords: database,ORM,peewee,mssql
Platform: UNKNOWN
Classifier: Development Status :: 4 - Beta
Classifier: Programming Language :: Python
Classifier: Programming Language :: Python :: 2.7
Classifier: License :: OSI Approved :: MIT License
Classifier: Topic :: Database
